heartlens_dataset_lib/Heartlens_datasetloader.py
heartlens_dataset_lib/__init__.py
heartlens_dataset_lib-0.1.1.dist-info/METADATA
heartlens_dataset_lib-0.1.1.dist-info/WHEEL
heartlens_dataset_lib-0.1.1.dist-info/top_level.txt
heartlens_dataset_lib-0.1.1.dist-info/RECORD
