Metadata-Version: 2.1
Name: heartlens_dataset_lib
Version: 0.1.1
Summary: Dataset Loader for Heartlens
Home-page: https://github.com/innovationcore/heartlens_dataset_library
Author: Mitchell Klusty
Author-email: mitchell.klusty@uky.edu
Classifier: Programming Language :: Python :: 3
Classifier: License :: OSI Approved :: MIT License
Classifier: Operating System :: OS Independent
Requires-Python: >=3.7
Requires-Dist: torch>=1.9.0
Requires-Dist: numpy>=1.21.0
Requires-Dist: zarr>=2.12.0
